caeroc/__init__.py
caeroc/cli.py
caeroc/logger.py
caeroc/_skaero/COPYING
caeroc/_skaero/__init__.py
caeroc/_skaero/constants.py
caeroc/_skaero/atmosphere/__init__.py
caeroc/_skaero/atmosphere/coesa.py
caeroc/_skaero/atmosphere/util.py
caeroc/_skaero/gasdynamics/__init__.py
caeroc/_skaero/gasdynamics/isentropic.py
caeroc/_skaero/gasdynamics/nozzles.py
caeroc/_skaero/gasdynamics/shocks.py
caeroc/_skaero/geometry/__init__.py
caeroc/_skaero/geometry/joukowsky.py
caeroc/_skaero/util/__init__.py
caeroc/_skaero/util/decorators.py
caeroc/formulae/__init__.py
caeroc/formulae/base.py
caeroc/formulae/duct.py
caeroc/formulae/isentropic.py
caeroc/formulae/shock.py
caeroc/gui/__init__.py
caeroc/gui/base.ui
caeroc/gui/base_pyqt.py
caeroc/gui/base_pyside2.py
caeroc/gui/configure
caeroc/gui/runtime.py
caeroc/profiles/__init__.py
caeroc/profiles/base.py
caeroc/util/__init__.py
caeroc/util/decorators.py
caeroc-0.0.3b1.dist-info/METADATA
caeroc-0.0.3b1.dist-info/WHEEL
caeroc-0.0.3b1.dist-info/entry_points.txt
caeroc-0.0.3b1.dist-info/licenses/LICENSE
caeroc-0.0.3b1.dist-info/licenses/src/caeroc/_skaero/COPYING
caeroc-0.0.3b1.dist-info/RECORD
