Metadata-Version: 2.3
Name: caeroc
Version: 0.0.3b1
Summary: Compressible aerodynamics calculator in Python
Project-URL: Homepage, https://github.org/ashwinvis/caeroc
Author-email: "Ashwin V. Mohanan" <dev@fluid.quest>
License: GPL
Keywords: calculator,compressible aerodynamics,gas dynamics
Classifier: Development Status :: 4 - Beta
Classifier: Intended Audience :: Education
Classifier: Intended Audience :: Science/Research
Classifier: License :: OSI Approved :: GNU General Public License v3 (GPLv3)
Classifier: Programming Language :: Python
Classifier: Programming Language :: Python :: 3
Classifier: Programming Language :: Python :: 3.10
Classifier: Topic :: Scientific/Engineering
Requires-Python: >=3.10
Requires-Dist: matplotlib>=3.5
Requires-Dist: numpy<2,>=1.21
Requires-Dist: pint>=0.18
Requires-Dist: qtpy>=2
Requires-Dist: scipy>=1.8
Provides-Extra: pyqt
Requires-Dist: pyqt5>=5.15; extra == 'pyqt'
Provides-Extra: pyside
Requires-Dist: pyside2>=5.15; extra == 'pyside'
